bionemo/testing/__init__.py
bionemo/testing/callbacks.py
bionemo/testing/lightning.py
bionemo/testing/megatron_dataset_compatibility.py
bionemo/testing/megatron_parallel_state_utils.py
bionemo/testing/subprocess_utils.py
bionemo/testing/testing_callbacks.py
bionemo/testing/torch.py
bionemo/testing/utils.py
bionemo/testing/data/__init__.py
bionemo/testing/data/esm2.py
bionemo/testing/data/fasta.py
bionemo/testing/data/load.py
bionemo/testing/data/resource.py
bionemo/testing/harnesses/__init__.py
bionemo/testing/harnesses/mode.py
bionemo/testing/harnesses/stop_and_go.py
bionemo_testing-2.4.1.dist-info/licenses/LICENSE
bionemo_testing-2.4.1.dist-info/METADATA
bionemo_testing-2.4.1.dist-info/WHEEL
bionemo_testing-2.4.1.dist-info/top_level.txt
bionemo_testing-2.4.1.dist-info/RECORD
