Metadata-Version: 2.4
Name: bionemo-testing
Version: 2.4.1
Summary: Utilities aiding test creation for BioNeMo sub-packages.
Author-email: BioNeMo Team <bionemofeedback@nvidia.com>
Requires-Python: >=3.10
License-File: LICENSE
Requires-Dist: bionemo-core
Requires-Dist: bionemo-llm
Requires-Dist: email-validator
Requires-Dist: pytest
Requires-Dist: overrides
Dynamic: license-file
